{
    "Ar36": {
        "error": 0.0035487900335662518, 
        "fit": "linear", 
        "value": 0.073658223367755765
    }, 
    "Ar37": {
        "error": 0.058763505321919235, 
        "fit": "linear", 
        "value": 0.25994809150142073
    }, 
    "Ar38": {
        "error": 0.17856091122772044, 
        "fit": "linear", 
        "value": 0.44211819369027561
    }, 
    "Ar39": {
        "error": 0.070750548979935282, 
        "fit": "linear", 
        "value": 21.035765342525366
    }, 
    "Ar40": {
        "error": 0.91517689683403036, 
        "fit": "linear", 
        "value": 5118.4856415980266
    }, 
    "Ar41": {
        "error": 0.13767553569850113, 
        "fit": "average_SEM", 
        "value": 0.13907485254885008
    }
}