{
    "Ar36": {
        "error": 0.0026001870264469513, 
        "fit": "linear", 
        "value": 0.03086647507543596
    }, 
    "Ar37": {
        "error": 0.060372966880312948, 
        "fit": "linear", 
        "value": 0.38696171572977239
    }, 
    "Ar38": {
        "error": 0.34008865066582661, 
        "fit": "linear", 
        "value": 0.63962927123960844
    }, 
    "Ar39": {
        "error": 0.88668232500310873, 
        "fit": "linear", 
        "value": 25.544097184094859
    }, 
    "Ar40": {
        "error": 0.065813178402064867, 
        "fit": "linear", 
        "value": 5110.9627555917359
    }, 
    "Ar41": {
        "error": 1.6348147053201183, 
        "fit": "average_SEM", 
        "value": 0.91890574909746647
    }
}